conjugate/__init__.py
conjugate/_beta_geometric.py
conjugate/_compound_gamma.py
conjugate/_typing.py
conjugate/distributions.py
conjugate/helpers.py
conjugate/interactive.py
conjugate/models.py
conjugate/plot.py
conjugate/py.typed
conjugate/slice.py
conjugate_models-0.14.0.dist-info/METADATA
conjugate_models-0.14.0.dist-info/WHEEL
conjugate_models-0.14.0.dist-info/licenses/LICENSE
conjugate_models-0.14.0.dist-info/RECORD
