Metadata-Version: 2.4
Name: conjugate-models
Version: 0.14.0
Summary: Bayesian Conjugate Models in Python
Project-URL: Homepage, https://williambdean.github.io/conjugate/
Project-URL: Repository, https://github.com/williambdean/conjugate
Project-URL: Documentation, https://williambdean.github.io/conjugate/
Author-email: Will Dean <wd60622@gmail.com>
License-Expression: MIT
License-File: LICENSE
Classifier: Intended Audience :: Developers
Classifier: Intended Audience :: Science/Research
Classifier: Operating System :: MacOS
Classifier: Operating System :: Microsoft :: Windows
Classifier: Operating System :: POSIX
Classifier: Operating System :: POSIX :: Linux
Classifier: Operating System :: Unix
Classifier: Programming Language :: Python
Classifier: Programming Language :: Python :: 3
Classifier: Programming Language :: Python :: 3.10
Classifier: Programming Language :: Python :: 3.11
Classifier: Programming Language :: Python :: 3.12
Classifier: Programming Language :: Python :: 3.13
Classifier: Programming Language :: Python :: 3.14
Classifier: Topic :: Scientific/Engineering
Classifier: Topic :: Software Development :: Libraries
Requires-Python: <4.0,>=3.10
Requires-Dist: matplotlib
Requires-Dist: numpy
Requires-Dist: packaging
Requires-Dist: scipy
